{
  "project_info": {
    "project_number": "951548002660",
    "project_id": "cismandi-b71b8",
    "storage_bucket": "cismandi-b71b8.appspot.com"
  },
  "client": [
    {
      "client_info": {
        "mobilesdk_app_id": "1:951548002660:android:db8bf8f2a2ed95e31c7a71",
        "android_client_info": {
          "package_name": "com.school.iqdigit.cismandi"
        }
      },
      "oauth_client": [
        {
          "client_id": "951548002660-ojmsd2el8ge4gadn4uk7oklfvs8r02fo.apps.googleusercontent.com",
          "client_type": 3
        }
      ],
      "api_key": [
        {
          "current_key": "AIzaSyBARJMtJP388uwnM3ojs9Idy8iJa_BD0nY"
        }
      ],
      "services": {
        "appinvite_service": {
          "other_platform_oauth_client": [
            {
              "client_id": "951548002660-ojmsd2el8ge4gadn4uk7oklfvs8r02fo.apps.googleusercontent.com",
              "client_type": 3
            }
          ]
        }
      }
    }
  ],
  "configuration_version": "1"
}